{
  "source": {
    "name": "Airframes Project",
    "url": "https://github.com/airframesio",
    "email": "kevin@airframes.io"
  },
  "attribution": {
    "name": "NOAA NWS Aviation Weather Center",
    "url": "https://aviationweather.gov/data/cache/airsigmets.cache.xml.gz"
  },
  "resource_type": "airsigmets",
  "count": 10,
  "airsigmets": [
    {
      "raw_text": null,
      "valid_time_from": "2026-06-15T05:55:00.000Z",
      "valid_time_to": "2026-06-15T07:55:00.000Z",
      "altitude": {
        "max_ft_msl": "45000"
      },
      "movement_dir_degrees": "270",
      "movement_spd_kt": "15",
      "hazard": {
        "type": "CONVECTIVE",
        "severity": "SEV"
      },
      "airsigmet_type": "SIGMET",
      "area": [
        {
          "point": {
            "longitude": "-111.5480",
            "latitude": "34.8030"
          }
        },
        {
          "point": {
            "longitude": "-107.0480",
            "latitude": "33.7450"
          }
        },
        {
          "point": {
            "longitude": "-107.0010",
            "latitude": "31.5640"
          }
        },
        {
          "point": {
            "longitude": "-110.9200",
            "latitude": "32.1000"
          }
        },
        {
          "point": {
            "longitude": "-112.7870",
            "latitude": "34.0850"
          }
        },
        {
          "point": {
            "longitude": "-111.5480",
            "latitude": "34.8030"
          }
        }
      ]
    },
    {
      "raw_text": null,
      "valid_time_from": "2026-06-15T05:55:00.000Z",
      "valid_time_to": "2026-06-15T07:55:00.000Z",
      "altitude": {
        "max_ft_msl": "45000"
      },
      "movement_dir_degrees": "160",
      "movement_spd_kt": "15",
      "hazard": {
        "type": "CONVECTIVE",
        "severity": "SEV"
      },
      "airsigmet_type": "SIGMET",
      "area": [
        {
          "point": {
            "longitude": "-97.1640",
            "latitude": "27.2860"
          }
        },
        {
          "point": {
            "longitude": "-96.5200",
            "latitude": "26.2370"
          }
        },
        {
          "point": {
            "longitude": "-97.7220",
            "latitude": "26.0470"
          }
        },
        {
          "point": {
            "longitude": "-98.2430",
            "latitude": "27.1930"
          }
        },
        {
          "point": {
            "longitude": "-97.1640",
            "latitude": "27.2860"
          }
        }
      ]
    },
    {
      "raw_text": null,
      "valid_time_from": "2026-06-15T05:55:00.000Z",
      "valid_time_to": "2026-06-15T07:55:00.000Z",
      "altitude": {
        "max_ft_msl": "45000"
      },
      "movement_dir_degrees": "300",
      "movement_spd_kt": "10",
      "hazard": {
        "type": "CONVECTIVE",
        "severity": "SEV"
      },
      "airsigmet_type": "SIGMET",
      "area": [
        {
          "point": {
            "longitude": "-96.3410",
            "latitude": "32.2770"
          }
        },
        {
          "point": {
            "longitude": "-94.9460",
            "latitude": "31.6250"
          }
        },
        {
          "point": {
            "longitude": "-99.2770",
            "latitude": "27.1730"
          }
        },
        {
          "point": {
            "longitude": "-102.0130",
            "latitude": "29.8010"
          }
        },
        {
          "point": {
            "longitude": "-101.0490",
            "latitude": "31.3790"
          }
        },
        {
          "point": {
            "longitude": "-96.3410",
            "latitude": "32.2770"
          }
        }
      ]
    },
    {
      "raw_text": null,
      "valid_time_from": "2026-06-15T05:55:00.000Z",
      "valid_time_to": "2026-06-15T07:55:00.000Z",
      "altitude": {
        "max_ft_msl": "35000"
      },
      "movement_dir_degrees": "280",
      "movement_spd_kt": "20",
      "hazard": {
        "type": "CONVECTIVE",
        "severity": "SEV"
      },
      "airsigmet_type": "SIGMET",
      "area": [
        {
          "point": {
            "longitude": "-88.2460",
            "latitude": "31.9090"
          }
        },
        {
          "point": {
            "longitude": "-87.0140",
            "latitude": "31.6270"
          }
        },
        {
          "point": {
            "longitude": "-87.0380",
            "latitude": "30.9570"
          }
        },
        {
          "point": {
            "longitude": "-88.5080",
            "latitude": "31.0370"
          }
        },
        {
          "point": {
            "longitude": "-88.2460",
            "latitude": "31.9090"
          }
        }
      ]
    },
    {
      "raw_text": null,
      "valid_time_from": "2026-06-15T05:55:00.000Z",
      "valid_time_to": "2026-06-15T07:55:00.000Z",
      "altitude": {
        "max_ft_msl": "39000"
      },
      "movement_dir_degrees": "220",
      "movement_spd_kt": "40",
      "hazard": {
        "type": "CONVECTIVE",
        "severity": "SEV"
      },
      "airsigmet_type": "SIGMET",
      "area": [
        {
          "point": {
            "longitude": "-67.9940",
            "latitude": "46.9280"
          }
        },
        {
          "point": {
            "longitude": "-71.8220",
            "latitude": "39.9980"
          }
        },
        {
          "point": {
            "longitude": "-74.8000",
            "latitude": "39.1000"
          }
        },
        {
          "point": {
            "longitude": "-76.2940",
            "latitude": "40.7710"
          }
        },
        {
          "point": {
            "longitude": "-73.0220",
            "latitude": "44.9910"
          }
        },
        {
          "point": {
            "longitude": "-67.9940",
            "latitude": "46.9280"
          }
        }
      ]
    },
    {
      "raw_text": null,
      "valid_time_from": "2026-06-15T05:55:00.000Z",
      "valid_time_to": "2026-06-15T07:55:00.000Z",
      "altitude": {
        "max_ft_msl": "45000"
      },
      "movement_dir_degrees": "270",
      "movement_spd_kt": "10",
      "hazard": {
        "type": "CONVECTIVE",
        "severity": "SEV"
      },
      "airsigmet_type": "SIGMET",
      "area": [
        {
          "point": {
            "longitude": "-78.7920",
            "latitude": "31.8230"
          }
        },
        {
          "point": {
            "longitude": "-77.1760",
            "latitude": "30.3860"
          }
        },
        {
          "point": {
            "longitude": "-78.3290",
            "latitude": "29.5430"
          }
        },
        {
          "point": {
            "longitude": "-79.7710",
            "latitude": "29.2930"
          }
        },
        {
          "point": {
            "longitude": "-79.8950",
            "latitude": "30.9040"
          }
        },
        {
          "point": {
            "longitude": "-78.7920",
            "latitude": "31.8230"
          }
        }
      ]
    },
    {
      "raw_text": null,
      "valid_time_from": "2026-06-15T05:55:00.000Z",
      "valid_time_to": "2026-06-15T07:55:00.000Z",
      "altitude": {
        "max_ft_msl": "45000"
      },
      "movement_dir_degrees": "280",
      "movement_spd_kt": "20",
      "hazard": {
        "type": "CONVECTIVE",
        "severity": "SEV"
      },
      "airsigmet_type": "SIGMET",
      "area": [
        {
          "point": {
            "longitude": "-81.2810",
            "latitude": "33.3950"
          }
        },
        {
          "point": {
            "longitude": "-80.5600",
            "latitude": "32.3510"
          }
        },
        {
          "point": {
            "longitude": "-85.1420",
            "latitude": "30.5580"
          }
        },
        {
          "point": {
            "longitude": "-87.0380",
            "latitude": "30.9570"
          }
        },
        {
          "point": {
            "longitude": "-87.0140",
            "latitude": "31.6270"
          }
        },
        {
          "point": {
            "longitude": "-81.2810",
            "latitude": "33.3950"
          }
        }
      ]
    },
    {
      "raw_text": null,
      "valid_time_from": "2026-06-15T05:55:00.000Z",
      "valid_time_to": "2026-06-15T07:55:00.000Z",
      "altitude": {
        "max_ft_msl": "45000"
      },
      "movement_dir_degrees": "160",
      "movement_spd_kt": "10",
      "hazard": {
        "type": "CONVECTIVE",
        "severity": "SEV"
      },
      "airsigmet_type": "SIGMET",
      "area": [
        {
          "point": {
            "longitude": "-95.9030",
            "latitude": "29.1150"
          }
        },
        {
          "point": {
            "longitude": "-94.5690",
            "latitude": "28.1130"
          }
        },
        {
          "point": {
            "longitude": "-95.4860",
            "latitude": "26.6090"
          }
        },
        {
          "point": {
            "longitude": "-97.0680",
            "latitude": "28.7580"
          }
        },
        {
          "point": {
            "longitude": "-95.9030",
            "latitude": "29.1150"
          }
        }
      ]
    },
    {
      "raw_text": null,
      "valid_time_from": "2026-06-15T05:55:00.000Z",
      "valid_time_to": "2026-06-15T07:55:00.000Z",
      "altitude": {
        "max_ft_msl": "43000"
      },
      "movement_dir_degrees": "300",
      "movement_spd_kt": "15",
      "hazard": {
        "type": "CONVECTIVE",
        "severity": "SEV"
      },
      "airsigmet_type": "SIGMET",
      "area": [
        {
          "point": {
            "longitude": "-107.0480",
            "latitude": "33.7450"
          }
        },
        {
          "point": {
            "longitude": "-105.1910",
            "latitude": "32.1970"
          }
        },
        {
          "point": {
            "longitude": "-105.2050",
            "latitude": "30.7410"
          }
        },
        {
          "point": {
            "longitude": "-107.0010",
            "latitude": "31.5640"
          }
        },
        {
          "point": {
            "longitude": "-107.0480",
            "latitude": "33.7450"
          }
        }
      ]
    },
    {
      "raw_text": null,
      "valid_time_from": "2026-06-15T05:55:00.000Z",
      "valid_time_to": "2026-06-15T07:55:00.000Z",
      "altitude": {
        "max_ft_msl": "32000"
      },
      "movement_dir_degrees": "300",
      "movement_spd_kt": "15",
      "hazard": {
        "type": "CONVECTIVE",
        "severity": "SEV"
      },
      "airsigmet_type": "SIGMET",
      "area": [
        {
          "point": {
            "longitude": "-104.4260",
            "latitude": "36.8450"
          }
        },
        {
          "point": {
            "longitude": "-104.5210",
            "latitude": "35.6580"
          }
        },
        {
          "point": {
            "longitude": "-106.5070",
            "latitude": "35.6540"
          }
        },
        {
          "point": {
            "longitude": "-106.6990",
            "latitude": "36.6420"
          }
        },
        {
          "point": {
            "longitude": "-104.4260",
            "latitude": "36.8450"
          }
        }
      ]
    }
  ]
}